MANIFEST.in
README.md
audio_plot.py
requirements.txt
setup.py
audio_plot.egg-info/PKG-INFO
audio_plot.egg-info/SOURCES.txt
audio_plot.egg-info/dependency_links.txt
audio_plot.egg-info/not-zip-safe
audio_plot.egg-info/requires.txt
audio_plot.egg-info/top_level.txt