Metadata-Version: 2.1
Name: audio-plot
Version: 0.0.2
Summary: Plot tools based on audio
Home-page: https://github.com/hassaku/audio-plot
Author: hassaku
Author-email: hassaku.apps@gmail.com
License: MIT
Keywords: audio plot visually-impaired
Platform: UNKNOWN
